chronopype/__init__.py
chronopype/clocks/__init__.py
chronopype/clocks/backtest.py
chronopype/clocks/base.py
chronopype/clocks/config.py
chronopype/clocks/modes.py
chronopype/clocks/realtime.py
chronopype/exceptions.py
chronopype/processors/__init__.py
chronopype/processors/base.py
chronopype/processors/models.py
chronopype/processors/network.py
chronopype/time.py
chronopype-0.2.9.dist-info/LICENSE
chronopype-0.2.9.dist-info/METADATA
chronopype-0.2.9.dist-info/WHEEL
chronopype-0.2.9.dist-info/RECORD
