Metadata-Version: 2.3
Name: chronopype
Version: 0.2.9
Summary: A flexible clock implementation for real-time and backtesting scenarios
Author: Gianluca Pagliara
Author-email: pagliara.gianluca@gmail.com
Requires-Python: >=3.13,<4.0
Classifier: Programming Language :: Python :: 3
Classifier: Programming Language :: Python :: 3.13
Requires-Dist: eventspype (>=1.0.1,<2.0.0)
Requires-Dist: pydantic (>=2.10.4,<3.0.0)
